mlio/__init__.py
mlio/io/__init__.py
mlio/io/_lib.py
mlio/io/compat.py
mlio/io/exc.py
mlio/io/pack.py
mlio/io/context_dependencies/__init__.py
mlio/io/context_dependencies/_registry.py
mlio/io/context_dependencies/base.py
mlio/io/context_dependencies/module_version.py
mlio/io/serializers/__init__.py
mlio/io/serializers/_registry.py
mlio/io/serializers/base.py
mlio/io/serializers/generic.py
mlio/io/serializers/gensim.py
mlio/resources/__init__.py
mlio/resources/exceptions.py
mlio/resources/manager.py
mlio/resources/repositories.py
mlio/resources/resource_types.py
mlio-0.9.1.dist-info/METADATA
mlio-0.9.1.dist-info/RECORD
mlio-0.9.1.dist-info/WHEEL
mlio-0.9.1.dist-info/top_level.txt
