Metadata-Version: 2.1
Name: mlio
Version: 0.9.1
Summary: I/O for machine learning
Home-page: UNKNOWN
Author: Konstantinos Paliouras
Author-email: paliouras@workable.com
License: UNKNOWN
Platform: UNKNOWN
Classifier: License :: OSI Approved :: MIT License
Classifier: Operating System :: OS Independent
Classifier: Programming Language :: Python
Classifier: Programming Language :: Python :: 3
Classifier: Topic :: Software Development :: Libraries :: Python Modules
Provides-Extra: test
Requires-Dist: joblib (~=0.11)
Requires-Dist: packaging (<17,>=16.8)
Requires-Dist: scikit-learn (>=0.17)
Provides-Extra: test
Requires-Dist: nose; extra == 'test'
Requires-Dist: coverage (~=4.3.4); extra == 'test'
Requires-Dist: gensim (~=2.3.0); extra == 'test'
Requires-Dist: xgboost (~=0.72); extra == 'test'
